src/__init__.py
src/remote_circles_storage.py
tests/__init__.py
tests/remote_circles_storage_test.py
storage_remote_python_client-0.0.1.dist-info/METADATA
storage_remote_python_client-0.0.1.dist-info/WHEEL
storage_remote_python_client-0.0.1.dist-info/top_level.txt
storage_remote_python_client-0.0.1.dist-info/RECORD
